alphavantage_api_client/__init__.py
alphavantage_api_client/__main__.py
alphavantage_api_client/client.py
alphavantage_api_client/models.py
alphavantage_api_client/response_validation_rules.py
alphavantage_api_client/ticker.py
alphavantage_api_client/version.py
examples/__init__.py
examples/getting_started.py
tests/__init__.py
tests/mock_client.py
tests/test_all_free_endpoints.py
tests/test_all_paid_endpoints.py
tests/test_base.py
tests/test_mock_client_units.py
tests/test_multi_client_integration.py
tests/test_multi_client_paid_integration.py
tests/test_single_client_integration.py
tests/test_single_client_limit_reached.py
alphavantage_api_client-2.4.0.dist-info/LICENSE
alphavantage_api_client-2.4.0.dist-info/METADATA
alphavantage_api_client-2.4.0.dist-info/WHEEL
alphavantage_api_client-2.4.0.dist-info/top_level.txt
alphavantage_api_client-2.4.0.dist-info/RECORD
