Metadata-Version: 2.1
Name: alphavantage-api-client
Version: 2.4.0
Summary: Interact with Alpha Vantage REST API
Home-page: https://github.com/xrgarcia/alphavantage-api-client
Author: Slashbin, LLC
Author-email: support@slashbin.us
License: MIT
Classifier: License :: OSI Approved :: MIT License
Classifier: Programming Language :: Python :: 3
Classifier: Operating System :: OS Independent
Requires-Python: >=3.9
License-File: LICENSE
Requires-Dist: requests
Requires-Dist: pydantic
